Metadata-Version: 1.0
Name: python-randomword
Version: 1.0.3
Summary: Cool simple Python module to get random words with definition (offline usage)
Home-page: https://github.com/remaudcorentin-dev/python-randomword
Author: Corentin Remaud
Author-email: remaudcorentin.dev@gmail.com
License: MIT
Platform: UNKNOWN
